{
  "id": "27-biography-memoir/political-and-military-leaders/the-autobiography-of-malcolm-x",
  "title": "The Autobiography of Malcolm X",
  "slug": "the-autobiography-of-malcolm-x",
  "authors": [
    "Malcolm X",
    "Alex Haley"
  ],
  "year": 1965,
  "category": "27-biography-memoir",
  "subcategory": "political-and-military-leaders",
  "pages": 496,
  "isbn": "978-0-345-35068-8",
  "publisher": "Grove Press",
  "language": "en",
  "genres": [
    "biography",
    "memoir",
    "civil-rights",
    "autobiography"
  ],
  "source": "generated",
  "generatedAt": "2026-06-12"
}
