{
  "slug": "attached-amir-levine",
  "title": "Attached: The New Science of Adult Attachment and How It Can Help You Find—and Keep—Love",
  "subtitle": "The definitive popular introduction to attachment theory in adult relationships.",
  "author": "Amir Levine & Rachel Heller",
  "publicationYear": 2010,
  "isbn": "9781585429134",
  "publisher": "TarcherPerigee",
  "language": "en",
  "pageCount": 304,
  "genres": ["Psychology", "Self-Help", "Relationships", "Science"],
  "subjects": ["Attachment Theory", "Relationships", "Romantic Love", "Social Psychology", "Personal Development"],
  "themes": [
    "The three attachment styles: Anxious, Avoidant, and Secure",
    "How childhood attachment patterns shape adult relationships",
    "Why opposites attract — and why the Anxious-Avoidant trap is so common",
    "How to identify attachment styles in yourself and partners",
    "The science of emotional bonding and relationship security"
  ],
  "tags": [
    "attachment", "relationships", "amir-levine", "attachment-theory",
    "anxious", "avoidant", "secure", "romantic-love",
    "psychology", "dating", "emotional-bonding"
  ],
  "difficulty": "easy",
  "estimatedReadingHours": 7,
  "estimatedListeningMinutes": 420,
  "awards": [
    "New York Times Bestseller"
  ],
  "excerpt": "Why do some people seem to navigate relationships with ease while others are trapped in patterns of anxiety and avoidance? Psychiatrist Amir Levine and psychologist Rachel Heller reveal that the answer lies in attachment theory — the science of how humans bond. Drawing on decades of research, they show that adult romantic relationships are governed by the same attachment system that bonds infants to caregivers. Understanding your attachment style — and your partner's — is the key to finding and keeping love."
}
