{
  "slug": "range-david-epstein",
  "title": "Range",
  "subtitle": "Why Generalists Triumph in a Specialized World",
  "author": "David Epstein",
  "publicationYear": 2019,
  "isbn": "9780735214484",
  "publisher": "Riverhead Books",
  "language": "en",
  "genres": ["Science", "Psychology", "Business", "Education"],
  "subjects": ["Expertise", "Specialization", "Generalism", "Innovation", "Cognitive Science", "Career Development"],
  "themes": ["Generalist vs Specialist", "Kind vs Wicked Learning Environments", "Match Quality", "Lateral Transfer", "Innovation", "Career Exploration"],
  "tags": ["expertise", "psychology", "education", "career", "specialization", "generalism", "innovation", "cognitive science", "10,000 hours", "deliberate practice"],
  "difficulty": "medium",
  "estimatedReadingHours": 7,
  "estimatedListeningMinutes": 480,
  "excerpt": "A counter-intuitive exploration of why breadth of experience beats depth in complex, unpredictable fields — and why the cult of early specialization is deeply flawed."
}
