{
  "slug": "the-conscious-mind-david-chalmers",
  "title": "The Conscious Mind",
  "subtitle": "In Search of a Fundamental Theory",
  "author": "David J. Chalmers",
  "publicationYear": 1996,
  "publisher": "Oxford University Press",
  "language": "en",
  "pageCount": 432,
  "isbn": "9780195117897",
  "genres": [
    "Philosophy",
    "Cognitive Science",
    "Neuroscience",
    "Science"
  ],
  "subjects": [
    "Consciousness",
    "Philosophy of mind",
    "Hard problem of consciousness",
    "Qualia",
    "Dualism",
    "Cognitive science",
    "Artificial consciousness"
  ],
  "themes": [
    "The hard problem of consciousness — why is there subjective experience at all? — is distinct from the easy problems of explaining cognitive functions",
    "Consciousness cannot be reductively explained in purely physical terms",
    "Naturalistic dualism: consciousness is a fundamental feature of the universe, like mass or charge",
    "Experience is not the same as function — explaining the function does not explain the experience",
    "Consciousness may be a fundamental property of information, not just of biological brains",
    "A complete theory of the universe must include consciousness as a fundamental element"
  ],
  "tags": [
    "consciousness",
    "philosophy-of-mind",
    "david-chalmers",
    "hard-problem",
    "qualia",
    "dualism",
    "experience",
    "zombies",
    "cognitive-science",
    "panpsychism",
    "fundamental-theory"
  ],
  "difficulty": "advanced",
  "estimatedReadingHours": 16,
  "estimatedListeningMinutes": 960,
  "excerpt": "Consciousness is the most familiar and the most mysterious phenomenon. But it is also something of an embarrassment for the physical sciences. No one has the foggiest idea how or why physical processes in the brain give rise to conscious experience. This explanatory gap is the central problem of consciousness. I call it the hard problem.",
  "cover": {
    "url": "https://covers.openlibrary.org/b/isbn/9780195117897-L.jpg"
  },
  "whoShouldRead": [],
  "whoShouldSkip": [],
  "keyIdeas": [],
  "keyTakeaways": [],
  "relatedBooks": []
}
