{
  "slug": "the-common-law-oliver-wendell-holmes",
  "title": "The Common Law Oliver Wendell Holmes",
  "language": "en",
  "difficulty": "medium",
  "excerpt": "The Common Law is not merely a legal history or a primer on doctrine — it is a philosophical manifesto delivered through meticulous legal archaeology. In twelve lectures originally given to a lay audience at Boston's Lowell Institute in 1880, Oliver Wendell Holmes Jr. excavated the origins of every ",
  "category": "08-society-history-and-power",
  "subcategory": "04-public-policy-and-civic-systems",
  "addedAt": 1781447993633,
  "tags": [
    "public-policy-and-civic-systems"
  ],
  "genres": [],
  "whoShouldRead": [],
  "whoShouldSkip": [],
  "keyIdeas": [],
  "keyTakeaways": [],
  "relatedBooks": [],
  "cover": {
    "url": "https://covers.openlibrary.org/b/isbn/-L.jpg"
  }
}
