{
  "slug": "the-way-of-the-superior-man-david-deida",
  "title": "The Way of the Superior Man: A Spiritual Guide to Mastering the Challenges of Women, Work, and Sexual Desire",
  "authors": ["David Deida"],
  "isbn13": "9781591792574",
  "isbn10": "1591792576",
  "year": 2008,
  "publisher": "Sounds True",
  "category": "04-self-help-personal-development",
  "subcategory": "mens-and-womens-development",
  "pages": 202,
  "language": "en",
  "genres": ["Self-Help", "Men's Development", "Spirituality", "Relationships"],
  "tags": ["masculinity", "men-development", "spirituality", "relationships", "sexuality", "purpose", "tantra"],
  "source": "generated",
  "generatedAt": "2026-06-12"
}
